Modulos de prueba/ROM/ROM.v
//Probar modulo ROM del procesador

module ROM(input wire [11:0] PC, output wire [7:0] program_byte);
        //Definimos las variables de entrada y salida.

    reg [7:0] memoria[0:4095]; //Asignamos el tamaño de la memoria
                              //la cual es de 4k con 8 bits de ancho

    initial begin
        $readmemh("memory.list", memoria); //guardamos un valor 
                                          //Hexadeximal en la memoria
    end

    assign program_byte = memoria[PC]; //Con PC se busca la localidad de memoria que se mostrara en la salida

endmodule

Modulos de prueba/ROM/ROM_tb.v
module testbench();

    reg [11:0] l;
    wire [7:0] y;

    ROM a(l, y);

    initial begin
        $display("Memoria ROM");
        $display("-Localidad- |----Dato----");
        $monitor("%b | %b", l, y);

        #1 l = 12'b000000000000;
        #1 l = 12'b000000000001;
        #1 l = 12'b000000000010;
        #1 l = 12'b000000000011;
        #1 l = 12'b000000000100;
        #1 l = 12'b000000000101;
        #1 l = 12'b000000000110;
        #1 l = 12'b000000000111;
        #1 l = 12'b000000001000;
        #1 l = 12'b000000001001;

    end

    initial
    #500 $finish;

    initial begin
        $dumpfile("ROM_tb.vcd");
        $dumpvars(0, testbench);
    end


endmodule

Modulos de prueba/ROM/ROM_tb.vcd
$date
	Sun Nov 22 13:35:18 2020
$end
$version
	Icarus Verilog
$end
$timescale
	1ps
$end
$scope module testbench $end
$var wire 8 ! y [7:0] $end
$var reg 12 " l [11:0] $end
$scope module a $end
$var wire 12 # PC [11:0] $end
$var wire 8 $ program_byte [7:0] $end
$upscope $end
$upscope $end
$enddefinitions $end
#0
$dumpvars
bx $
bx #
bx "
bx !
$end
#1
b1001111 !
b1001111 $
b0 "
b0 #
#2
b11011111 !
b11011111 $
b1 "
b1 #
#3
b1010001 !
b1010001 $
b10 "
b10 #
#4
b1000000 !
b1000000 $
b11 "
b11 #
#5
b1001111 !
b1001111 $
b100 "
b100 #
#6
b10101010 !
b10101010 $
b101 "
b101 #
#7
b101000 !
b101000 $
b110 "
b110 #
#8
b1001010 !
b1001010 $
b111 "
b111 #
#9
b101100 !
b101100 $
b1000 "
b1000 #
#10
b10100001 !
b10100001 $
b1001 "
b1001 #
