Modulos de prueba/RAM/RAM.v
//Tester Ram del procesador
module RAM (input[11:0] address_RAM, input csRAM, weRAM, output [3:0] saved_data);

    reg [3:0] memoria[0:4095]; //Localidades de memoria de la RAM
    reg [3:0] salida_datos;

    assign saved_data = (csRAM && ! weRAM) ? salida_datos : 4'bzzzz; //Control del bufer triestado
                                                                     //Sale cuando weRAM es 0 y cuando csRAM es igual a 1

    //Escritura dentro de la memoria
    always @ (address_RAM or saved_data or csRAM or weRAM) begin: MEM_WRITE
        if (csRAM && weRAM)
            memoria[address_RAM] = saved_data;
    end

    //Lectura de lo que esta en la memoria RAM
    always @ (address_RAM or csRAM or weRAM) begin: MEM_READ
        if (csRAM && ! weRAM)
            salida_datos = memoria[address_RAM];
    end

endmodule

Modulos de prueba/RAM/RAM_tb.v
module testbench();

  logic csRAM, weRAM;
  logic [3:0] datain;
  logic [11:0] address_RAM;
  wire [3:0] saved_data;

  RAM ram(address_RAM, csRAM, weRAM, saved_data);

  initial
  #200 $finish;

  assign data = weRAM ? datain: 4'bz;

  initial begin
  $display("Address | Data");
  $monitor("%b | %b", address_RAM, saved_data);
  csRAM = 1; weRAM = 0;
  $display("Leyendo...");
  #1 address_RAM = 12'h000;
  #1 address_RAM = 12'h001;
  #1 address_RAM = 12'h002;

  $display("Escribiendo...");
  #1 weRAM = 1; datain = 4'b1010; address_RAM = 12'h000;
  #1 datain = 4'b1011; address_RAM = 12'h001;
  #1 datain = 4'b1100; address_RAM = 12'h002;

  $display("Leyendo...");
  #1 address_RAM = 12'h000; weRAM = 0;
  #1 address_RAM = 12'h001;
  #1 address_RAM = 12'h002;

  end

  initial begin
    $dumpfile("RAM_tb.vcd");
    $dumpvars(0, testbench);
  end


endmodule

Modulos de prueba/RAM/RAM_tb.vcd
$date
	Sun Nov 22 17:58:16 2020
$end
$version
	Icarus Verilog
$end
$timescale
	1ps
$end
$scope module testbench $end
$var wire 4 ! saved_data [3:0] $end
$var wire 1 " data $end
$var reg 12 # address_RAM [11:0] $end
$var reg 1 $ csRAM $end
$var reg 4 % datain [3:0] $end
$var reg 1 & weRAM $end
$scope module ram $end
$var wire 12 ' address_RAM [11:0] $end
$var wire 1 $ csRAM $end
$var wire 1 & weRAM $end
$var wire 4 ( saved_data [3:0] $end
$var reg 4 ) salida_datos [3:0] $end
$scope begin MEM_READ $end
$upscope $end
$scope begin MEM_WRITE $end
$upscope $end
$upscope $end
$upscope $end
$enddefinitions $end
#0
$dumpvars
bx )
bx (
bx '
0&
bx %
1$
bx #
z"
bx !
$end
#1
b0 #
b0 '
#2
b1 #
b1 '
#3
b10 #
b10 '
#4
0"
bz !
bz (
b0 #
b0 '
b1010 %
1&
#5
1"
b1 #
b1 '
b1011 %
#6
0"
b10 #
b10 '
b1100 %
#7
z"
bz )
0&
b0 #
b0 '
#8
b1 #
b1 '
#9
b10 #
b10 '
