Modulos de prueba/ALU/ALU.v
//Tester ALU del procesador
module ALU(input [2:0] f, input [3:0] a, b, output carry, zero, output [3:0] s);

    reg [4:0] control; //variable que nos ayudara a realizar tanto las operaciones como verificar el estado de zero y carry

    always @ (a, b, f)
        case(f)
            3'b000: control = a; //out, jumps y st
            3'b001: control = a - b; //CMPI y CMPM
            3'b010: control = b; //LIT, in y ld
            3'b011: control = a + b; //ADDI y ADDM
            3'b100: control = {1'b0, ~(a & b)}; //NANDI y NANDM
            default: control = 5'b10101;//valor por defecto de controll si la instruccion no se encuentra
        endcase

    assign s = control[3:0];//salida de la ALU despues de operar
    assign carry = control[4]; //Bit si existe overflow en la operación
    assign zero = ~(control[3] | control[2] | control[1] | control[0]); //Bit que se enciende cuando la salida S es igual a 0

endmodule

Modulos de prueba/ALU/ALU_tb.v
module testbench();

    wire carry, zero;
    reg [3:0] a, b;
    reg [2:0] f;
    wire [3:0] y;

    ALU m(f, a, b, carry, zero, y);


    initial begin
    $display("ALU");
    $display("A | B | F | Carry | Zero | Salida");
    $monitor("%b | %b | %b | %b | %b | %b", a, b, f, carry, zero, y);

       a = 4'b0000; b = 4'b0000; f = 3'b000;
    #1 a = 4'b0001; b = 4'b0000; f = 3'b000;
    #1 a = 4'b0001; b = 4'b0001; f = 3'b000;
    #1 a = 4'b0000; b = 4'b0000; f = 3'b001;
    #1 a = 4'b0000; b = 4'b0001; f = 3'b001;
    #1 a = 4'b0001; b = 4'b0001; f = 3'b001;
    #1 a = 4'b1000; b = 4'b0100; f = 3'b010;
    #1 a = 4'b1000; b = 4'b0100; f = 3'b010;
    #1 a = 4'b0000; b = 4'b0100; f = 3'b011;
    #1 a = 4'b0000; b = 4'b0100; f = 3'b011;
    #1 a = 4'b0010; b = 4'b0000; f = 3'b100;
    #1 a = 4'b0010; b = 4'b0000; f = 3'b100;

    end

    initial
        #30 $finish;

    initial begin
        $dumpfile("ALU_tb.vcd");
        $dumpvars(0, testbench);
    end


endmodule

Modulos de prueba/ALU/ALU_tb.vcd
$date
	Sun Nov 22 13:38:13 2020
$end
$version
	Icarus Verilog
$end
$timescale
	1ps
$end
$scope module testbench $end
$var wire 1 ! zero $end
$var wire 4 " y [3:0] $end
$var wire 1 # carry $end
$var reg 4 $ a [3:0] $end
$var reg 4 % b [3:0] $end
$var reg 3 & f [2:0] $end
$scope module m $end
$var wire 4 ' a [3:0] $end
$var wire 4 ( b [3:0] $end
$var wire 3 ) f [2:0] $end
$var wire 1 ! zero $end
$var wire 4 * s [3:0] $end
$var wire 1 # carry $end
$var reg 5 + control [4:0] $end
$upscope $end
$upscope $end
$enddefinitions $end
#0
$dumpvars
b0 +
b0 *
b0 )
b0 (
b0 '
b0 &
b0 %
b0 $
0#
b0 "
1!
$end
#1
0!
b1 "
b1 *
b1 +
b1 $
b1 '
#2
b1 %
b1 (
#3
1!
b0 "
b0 *
b0 +
b1 &
b1 )
b0 %
b0 (
b0 $
b0 '
#4
0!
b1111 "
b1111 *
1#
b11111 +
b1 %
b1 (
#5
1!
b0 "
b0 *
0#
b0 +
b1 $
b1 '
#6
0!
b100 "
b100 *
b100 +
b10 &
b10 )
b100 %
b100 (
b1000 $
b1000 '
#8
b11 &
b11 )
b0 $
b0 '
#10
b1111 "
b1111 *
b1111 +
b100 &
b100 )
b0 %
b0 (
b10 $
b10 '
